Workbook

Sheet 交付说明
A1: 纯T2V模型能力定义型评测｜V6检查点拆解
A3: 来源题表 | B3: /Users/lvruofan1/Desktop/t2v-10s.xlsx
A4: 规则说明 | B4: 纯T2V模型能力定义型评测_完整说明_V6.docx
A5: 标签树 | B5: 纯T2V能力项与完整标签树_V6.xlsx
A6: 题目数 | B6: 448
A7: 检查点数 | B7: 2943
A8: 每题检查点范围 | B8: 2–12
A9: 平均检查点/题 | B9: 6.5691964
A10: 数量自检异常 | B10: 0
A11: 唯一映射异常 | B11: 0
A12: 重复标签异常 | B12: 0
A14: 使用说明
A15: 原题完整保存在“原题”表；“检查点拆解”仅定义检查点，不对生成结果打C/R/N。声音、音乐、音效与不可见台词语义只在预处理说明中记录。
A16: “自检”表逐题检查2–12点、唯一映射、重复标签、声音泄漏与最低成功线；复杂题已标记为建议全检。

Sheet 原题
A1: 题目ID | B1: 原序号 | C1: 原Prompt（保留原文） | D1: 语言 | E1: 预处理说明
A2: Q0001 | B2: 1 | C2: Starting from a wide shot pushing in, a tall and sturdy oak tree with lush foliage. The camera cuts to a close-up in the tree where a squirrel and a chipmunk are busy building a treehouse. The chipmunk holds a blueprint while the squirrel hammers nails intently. 3D cartoon style. | D2: 英文 | E2: 无范围外声音或不可见台词要求；原Prompt保留不改写。
A3: Q0002 | B3: 2 | C3: A thick morning fog shrouds a medieval muddy training ground near a stone castle. Three fully armored knights face off in a triangular formation, lances raised. At a herald's trumpet blast, two charge forward and clash with a forceful collision, mud splashing beneath their boots, one lance splintering on impact. The third knight circles behind and strikes the stumbling loser across the back with a mace, knocking him face-first into the mud. The remaining two engage in close combat — swords drawn, trading blows, each hit sending sparks and denting the metal surface. One disarms the other with a sweeping strike; the disarmed knight grabs a shield from the mud and blocks a downward slash. From the castle wall above, spectators cheer and a lady drops a red favor. The camera tracks low through the mud, capturing the metallic sheen of dented armor, breath misting in cold air, and blood mixing with muddy water. The victor raises his sword overhead, fog swirling around him. | D3: 英文 | E3: 已删除声音、音乐、音效或环境音要求，不生成声音检查点。
A4: Q0003 | B4: 3 | C4: 【俯拍・升格】指尖轻触屏幕，京东 APP 图标被点亮，光纹瞬间扩散 【航拍・流光】城市车流如星河，京东配送车穿行其中，尾灯拉出光轨 【逆光・远景】无人机从楼顶升空，划破天际，飞向城市远方 【轨道・纵深】智能仓内，机械臂精准运转，AGV 机器人列队穿梭，包裹如流水前行、【航拍・晨昏】北京 CBD 天际线，晨光洒在京东物流枢纽 【街拍・暖光】上海街头，配送车驶过梧桐树下，光影温柔 【蒙太奇・异域】海外都市：曼谷街巷、伦敦街区、迪拜新城，京东元素自然融入 【特写・柔光】用户签收包裹，指尖触到包装，抬头微笑，眼神明亮治愈 | D4: 中文/含中文 | E4: 无范围外声音或不可见台词要求；原Prompt保留不改写。
A5: Q0004 | B5: 4 | C5: A telephoto lens compresses depth, capturing the endless stream of commuters on a rush-hour overpass. A suited man in the foreground strides past creating motion blur, while the dense crowd and distant office tower glass walls catching morning light fill the background. | D5: 英文 | E5: 无范围外声音或不可见台词要求；原Prompt保留不改写。
A6: Q0005 | B6: 5 | C6: Grandma making dumplings in the kitchen, her technique practiced and skilled. | D6: 英文 | E6: 无范围外声音或不可见台词要求；原Prompt保留不改写。
A7: Q0006 | B7: 6 | C7: Generate a 15-second high-energy summer commercial video. On a hot summer day, the city is baked by the intense sun, heat rises from the ground, and a heatwave distortion effect is visible in the air. Indoors at home or in an office, a person is sweating profusely, dry-mouthed, and says, "It's way too hot, I need something iced!" They open their phone and place an order on [JD Miaosong] for cold beer, iced drinks, ice cream, and other items. The phone screen rapidly flashes "Order Successful" and "Nearest warehouse responding instantly." Fast-paced visual rhythm, bright colors, emphasizing the intense summer heat and strong thirst, driving the audience to want to order cold drinks immediately. Commercial advertising style, exaggerated, exciting, and highly satisfying. | D7: 英文 | E7: 已删除不可见台词/歌词语义及准确内容核验；仅保留可见开口、口型或回应动作。
A8: Q0007 | B8: 7 | C8: A wide-angle, low-angle hyper-realistic shot of astronauts floating weightlessly through the illuminated corridor of a high-tech spaceship, with the camera slowly tracking their slow-motion movements. | D8: 英文 | E8: 无范围外声音或不可见台词要求；原Prompt保留不改写。
A9: Q0008 | B9: 8 | C9: Wide-angle low-angle hyper-realistic shot. Several astronauts float weightlessly through a glowing high-tech spacecraft corridor. The camera slowly tracks their slow-motion drifting movements. The overall scene carries a futuristic sci-fi atmosphere, fine details, 8K cinematic quality. | D9: 英文 | E9: 无范围外声音或不可见台词要求；原Prompt保留不改写。
A10: Q0009 | B10: 9 | C10: Timelapse photography records a city transitioning from day to night — skyscraper lights turning on one by one, traffic forming continuous light trails. Cut to a mountain summit where timelapse continues capturing the Milky Way slowly rotating until the first dawn light strikes the peak. | D10: 英文 | E10: 无范围外声音或不可见台词要求；原Prompt保留不改写。
A11: Q0010 | B11: 10 | C11: Inside a dim cavern, translucent water droplets slowly form at the tip of a moist limestone stalactite and fall, splashing into a tiny burst on the stone floor below. | D11: 英文 | E11: 无范围外声音或不可见台词要求；原Prompt保留不改写。
A12: Q0011 | B12: 11 | C12: 镜头1 一台工业机械臂在流水线上快速抓起一块金属零件，转动手腕后放到传送带上。传送带持续运行，两侧多个滚轮同步转动，后方另一台机械臂正在焊接，焊花四溅，镜头跟随主机械臂平滑移动。 镜头2 镜头切到侧前方，零件沿传送带前进，经过检测装置时指示灯亮起，分拣机械臂迅速伸出将零件夹起并放入料箱。传送带、滚轮、机械臂和背景设备持续协同运转，焊花、指示灯、金属反光和轻微震动同步变化，整体动作连贯，符合真实机械传动和物理规律。 | D12: 中文/含中文 | E12: 无范围外声音或不可见台词要求；原Prompt保留不改写。
A13: Q0012 | B13: 12 | C13: 超写实电影质感，4K，杜比视界色彩，自然光照，中景固定镜头 男士身着卡其冲锋衣搭橄榄抓绒内搭，配深灰工装裤、黑登山靴，背负军绿登山包并系战术腰封，全套专业户外工装穿搭。他来到沙滩树下盘腿坐地，演示“弓钻取火”——快速拉动弓弦，钻头冒烟，黑炭火种落入干棕榈纤维，他轻轻吹气，“呼”的一声烟从棕榈纤维蹿起。棕榈纤维中透出火星的光点，他小心翼翼捧起火绒凑近镜头，笑着介绍“耐心一点火种很快就有了” | D13: 中文/含中文 | E13: 已删除不可见台词/歌词语义及准确内容核验；仅保留可见开口、口型或回应动作。
... A449: Q0448 | B449: 448 | C449: 动漫风格，樱花飞舞的神社台阶上，两名忍者高速对决。一人掷出三枚手里剑被对方侧身闪过，随即两人贴身以苦无对击，火花四溅。其中一人后空翻拉开距离，双手结印喷出火焰；另一人以水盾抵挡，蒸汽弥漫整个画面。 | D449: 中文/含中文 | E449: 无范围外声音或不可见台词要求；原Prompt保留不改写。

Sheet 检查点拆解
A1: 题目ID | B1: 检查点ID | C1: 原子检查点 | D1: 核心能力ID | E1: 核心能力名称 | F1: 三级标签ID | G1: 三级标签名称 | H1: 最低成功线 | I1: 证据时段（如有） | J1: 预处理说明
A2: Q0001 | B2: Q0001-CP01 | C2: 按原题形成双镜头或多镜头结构与转场 | D2: C30 | E2: 长镜头多镜头叙事与视觉特效 | F2: D15.01.02 | G2: 多镜头结构与转场 | H2: 能辨认出原题要求的主要镜头段，切换顺序与转场类型大体成立，不合并成无切换的单段。 | I2: 全片 | J2: 无范围外声音或不可见台词要求；原Prompt保留不改写。
A3: Q0001 | B3: Q0001-CP02 | C3: 按工具功能完成加工、修理或书写操作 | D3: C18 | E3: 人-物与专业器械操作 | F3: D07.01.02 | G3: 工具使用与加工操作 | H3: 工具握持方向和作用点合理，至少一次操作产生原题要求的可见结果。 | I3: 工具操作段 | J3: 无范围外声音或不可见台词要求；原Prompt保留不改写。
A4: Q0001 | B4: Q0001-CP03 | C4: 保持角色、道具、场景或动作在切镜后的连续承接 | D4: C30 | E4: 长镜头多镜头叙事与视觉特效 | F4: D15.01.03 | G4: 跨镜头连续性 | H4: 切镜前后主要角色身份、服装、道具所有者与动作状态可对应，不无故换人换物或重置。 | I4: 相邻切镜前后 | J4: 无范围外声音或不可见台词要求；原Prompt保留不改写。
A5: Q0001 | B5: Q0001-CP04 | C5: 执行相机平移、升降或前推后拉 | D5: C27 | E5: 镜头与摄影控制 | F5: D11.01.02 | G5: 平移升降与前推后拉 | H5: 相机位移方向与原题一致，主体尺度和背景视差随位移连续变化。 | I5: 运镜段 | J5: 无范围外声音或不可见台词要求；原Prompt保留不改写。
A6: Q0001 | B6: Q0001-CP05 | C6: 维持原题指定的三维动画、定格或手工媒介 | D6: C28 | E6: 构图光照材质与风格媒介 | F6: D13.02.01 | G6: 三维动画定格与手工媒介 | H6: 模型/手工材质与运动方式可辨，全片不突然切换为写实摄影或二维画面。 | I6: 全片 | J6: 无范围外声音或不可见台词要求；原Prompt保留不改写。
A7: Q0001 | B7: Q0001-CP06 | C7: 保持原题指定景别、角度与前中后景构图 | D7: C28 | E7: 构图光照材质与风格媒介 | F7: D12.01.01 | G7: 画面构图与空间层次 | H7: 主要主体的画面位置、景别和俯仰/远近关系与原题一致，构图不在关键段无故漂移。 | I7: 构图要求对应段 | J7: 无范围外声音或不可见台词要求；原Prompt保留不改写。
A8: Q0001 | B8: Q0001-CP07 | C8: 生成原题指定物种的动物或生物主体 | D8: C04 | E8: 动物物体载具主体生成 | F8: D02.02.01 | G8: 动物与生物主体 | H8: 主要动物的物种可辨，关键肢体、表皮与器官数量基本正确，不被相近物种替换。 | I8: 动物清晰出现段 | J8: 无范围外声音或不可见台词要求；原Prompt保留不改写。
A9: Q0002 | B9: Q0002-CP01 | C9: 完成原题指定的武器或徒手连续攻防 | D9: C20 | E9: 武器与徒手打斗 | F9: D07.02.04 | G9: 武器与徒手打斗 | H9: 至少一组攻击—防守/命中—反馈链清楚，武器或肢体轨迹对准对手且不无故穿体。 | I9: 攻防动作段 | J9: 已删除声音、音乐、音效或环境音要求，不生成声音检查点。
A10: Q0002 | B10: Q0002-CP02 | C10: 按原题保持指定数量的主要主体 | D10: C14 | E10: 多主体容量与精确数量 | F10: D08.01.01 | G10: 可数主体精确控制 | H10: 主要主体同时清晰可数时数量与原题一致，且关键时段不持续增减或融合。 | I10: 主体同时清晰出现段 | J10: 已删除声音、音乐、音效或环境音要求，不生成声音检查点。
A11: Q0002 | B11: Q0002-CP03 | C11: 呈现碰撞、命中与动量反作用 | D11: C23 | E11: 刚体接触轨迹与碰撞物理 | F11: D09.01.02 | G11: 碰撞动量与反作用 | H11: 碰撞双方在同一时空接触，受击体产生与方向、力度相符的位移、变形或反弹。 | I11: 碰撞发生段 | J11: 已删除声音、音乐、音效或环境音要求，不生成声音检查点。
A12: Q0002 | B12: Q0002-CP04 | C12: 呈现液体流动、飞溅或容器边界 | D12: C24 | E12: 柔体流体状态变化与世界因果 | F12: D09.02.02 | G12: 液体流动与容器边界 | H12: 液体随重力连续流动，飞溅/波纹从接触点扩散，受容器或表面边界约束。 | I12: 液体运动段 | J12: 已删除声音、音乐、音效或环境音要求，不生成声音检查点。
... A2944: Q0448 | B2944: Q0448-CP06 | C2944: 按地形、台阶或障碍调整人体移动 | D2944: C08 | E2944: 整体人体结构与基础移动 | F2944: D04.01.03 | G2944: 台阶地形与障碍移动 | H2944: 脚步与坡度/台阶/障碍形成接触，抬腿、步幅和重心随地形变化，不明显穿地。 | I2944: 复杂地形移动段 | J2944: 无范围外声音或不可见台词要求；原Prompt保留不改写。

Sheet 自检
A1: 题目ID | B1: 检查点数 | C1: 2–12点 | D1: V6唯一映射 | E1: 题内标签不重复 | F1: 声音要求已移除 | G1: 最低成功线可执行 | H1: 抽检建议
A2: Q0001 | B2: 7 | C2: 通过 | D2: 通过 | E2: 通过 | F2: 通过 | G2: 通过 | H2: 常规抽检
A3: Q0002 | B3: 12 | C3: 通过 | D3: 通过 | E3: 通过 | F3: 通过 | G3: 通过 | H3: 复杂题：建议全检
A4: Q0003 | B4: 8 | C4: 通过 | D4: 通过 | E4: 通过 | F4: 通过 | G4: 通过 | H4: 常规抽检
A5: Q0004 | B5: 8 | C5: 通过 | D5: 通过 | E5: 通过 | F5: 通过 | G5: 通过 | H5: 常规抽检
A6: Q0005 | B6: 4 | C6: 通过 | D6: 通过 | E6: 通过 | F6: 通过 | G6: 通过 | H6: 常规抽检
A7: Q0006 | B7: 12 | C7: 通过 | D7: 通过 | E7: 通过 | F7: 通过 | G7: 通过 | H7: 复杂题：建议全检
A8: Q0007 | B8: 8 | C8: 通过 | D8: 通过 | E8: 通过 | F8: 通过 | G8: 通过 | H8: 常规抽检
A9: Q0008 | B9: 8 | C9: 通过 | D9: 通过 | E9: 通过 | F9: 通过 | G9: 通过 | H9: 常规抽检
A10: Q0009 | B10: 5 | C10: 通过 | D10: 通过 | E10: 通过 | F10: 通过 | G10: 通过 | H10: 常规抽检
A11: Q0010 | B11: 4 | C11: 通过 | D11: 通过 | E11: 通过 | F11: 通过 | G11: 通过 | H11: 常规抽检
A12: Q0011 | B12: 8 | C12: 通过 | D12: 通过 | E12: 通过 | F12: 通过 | G12: 通过 | H12: 常规抽检
A13: Q0012 | B13: 8 | C13: 通过 | D13: 通过 | E13: 通过 | F13: 通过 | G13: 通过 | H13: 常规抽检
... A449: Q0448 | B449: 6 | C449: 通过 | D449: 通过 | E449: 通过 | F449: 通过 | G449: 通过 | H449: 常规抽检

Sheet V6唯一映射
A1: 三级标签ID | B1: 三级标签名称 | C1: 核心能力ID | D1: 核心能力名称 | E1: 能力描述
A2: D01.01.01 | B2: 常见直接指令理解 | C2: C01 | D2: 指令语义与排除约束 | E2: 准确识别主体、动作、场景和基础视觉要求。
A3: D01.01.02 | B3: 长尾与专业概念理解 | C3: C01 | D3: 指令语义与排除约束 | E3: 理解低频实体、专业器械、历史物件和影视术语。
A4: D01.01.03 | B4: 否定与排除约束 | C4: C01 | D4: 指令语义与排除约束 | E4: 执行“不出现、不要变化、保持静止”等排除条件。
A5: D01.01.04 | B5: 指代与角色消歧 | C5: C01 | D5: 指令语义与排除约束 | E5: 正确解析前者/后者、左侧人物和同一对象等指代。
A6: D01.02.01 | B6: 多条件组合遵循 | C6: C02 | D6: 组合约束与时序理解 | E6: 同时满足多个主体、属性、动作、场景、镜头和风格条件。
A7: D01.02.02 | B7: 结构化时序指令理解 | C7: C02 | D7: 组合约束与时序理解 | E7: 执行带阶段、时间词或分段描述的动作计划。
A8: D01.02.03 | B8: 开放Prompt合理补全 | C8: C02 | D8: 组合约束与时序理解 | E8: 在短提示未写全时补出合理运动、环境细节和视觉连续性。
A9: D02.01.01 | B9: 写实人物主体 | C9: C03 | D9: 人物与角色主体生成 | E9: 生成真实五官、皮肤、毛发和完整人体结构。
A10: D02.01.02 | B10: 风格化人物角色 | C10: C03 | D10: 人物与角色主体生成 | E10: 稳定生成动漫、卡通、游戏和CG人物结构。
A11: D02.01.03 | B11: 人物多样性与特殊形态 | C11: C03 | D11: 人物与角色主体生成 | E11: 覆盖年龄、体型、服饰、辅助器具和非典型身体特征。
A12: D02.02.01 | B12: 动物与生物主体 | C12: C04 | D12: 动物物体载具主体生成 | E12: 生成不同物种的骨骼、外形、表皮和关键器官。
... A101: D15.02.01 | B101: 动态特效与超现实变形 | C101: C30 | D101: 长镜头多镜头叙事与视觉特效 | E101: 生成粒子、能量、魔法、材质变换、空间扭曲和大型奇观的连续过程。

Sheet 覆盖概览
A1: 纯T2V V6检查点拆解｜覆盖统计
A3: 统计指标 | B3: 结果
A4: 题目总数 | B4: =COUNTA(原题!$A$2:$A$449) -> 448
A5: 检查点总数 | B5: =COUNTA(检查点拆解!$B$2:$B$2944) -> 2943
A6: 平均检查点/题 | B6: =B5/B4 -> 6.5691964
A7: 核心能力覆盖 | B7: =COUNTIF(核心能力覆盖!$E$2:$E$31,">0")&"/30" -> 29/30
A8: 三级标签覆盖 | B8: =COUNTIF(三级标签覆盖!$F$2:$F$101,">0")&"/100" -> 91/100
A9: 未覆盖三级标签数 | B9: =COUNTIF(三级标签覆盖!$F$2:$F$101,0) -> 9
A11: 统计口径
A12: 题目覆盖数＝至少包含1个对应能力/标签检查点的去重题目数；检查点数＝实际原子计分单元数。覆盖率只描述当前题库分布，不代表能力权重已经均衡，也不替代题目质量审查。三级标签按V6全部100项列示，0即为明确缺口。
A16: 独立核对结果 | B16: 数值
A17: JS去重题目数 | B17: 448
A18: JS检查点数 | B18: 2943

Sheet 核心能力覆盖
A1: 核心能力ID | B1: 核心能力名称 | C1: 题目覆盖数 | D1: 题目覆盖率 | E1: 检查点数 | F1: 检查点占比 | G1: 已覆盖三级标签 | H1: 三级标签总数 | I1: 标签覆盖率 | J1: 每覆盖题检查点数
A2: C01 | B2: 指令语义与排除约束 | C2: =SUMIF(统计辅助_勿改!$B$2:$B$2944,$A2,统计辅助_勿改!$C$2:$C$2944) -> 15 | D2: =C2/覆盖概览!$B$4 -> 0.033482143 | E2: =COUNTIF(检查点拆解!$D$2:$D$2944,$A2) -> 15 | F2: =E2/覆盖概览!$B$5 -> 0.00509684 | G2: =COUNTIFS(三级标签覆盖!$A$2:$A$101,$A2,三级标签覆盖!$F$2:$F$101,">0") -> 2 | H2: =COUNTIF(V6唯一映射!$C$2:$C$101,$A2) -> 4 | I2: =G2/H2 -> 0.5 | J2: =IF(C2=0,0,E2/C2) -> 1
A3: C02 | B3: 组合约束与时序理解 | C3: =SUMIF(统计辅助_勿改!$B$2:$B$2944,$A3,统计辅助_勿改!$C$2:$C$2944) -> 3 | D3: =C3/覆盖概览!$B$4 -> 0.0066964286 | E3: =COUNTIF(检查点拆解!$D$2:$D$2944,$A3) -> 3 | F3: =E3/覆盖概览!$B$5 -> 0.001019368 | G3: =COUNTIFS(三级标签覆盖!$A$2:$A$101,$A3,三级标签覆盖!$F$2:$F$101,">0") -> 2 | H3: =COUNTIF(V6唯一映射!$C$2:$C$101,$A3) -> 3 | I3: =G3/H3 -> 0.66666667 | J3: =IF(C3=0,0,E3/C3) -> 1
A4: C03 | B4: 人物与角色主体生成 | C4: =SUMIF(统计辅助_勿改!$B$2:$B$2944,$A4,统计辅助_勿改!$C$2:$C$2944) -> 73 | D4: =C4/覆盖概览!$B$4 -> 0.16294643 | E4: =COUNTIF(检查点拆解!$D$2:$D$2944,$A4) -> 73 | F4: =E4/覆盖概览!$B$5 -> 0.024804621 | G4: =COUNTIFS(三级标签覆盖!$A$2:$A$101,$A4,三级标签覆盖!$F$2:$F$101,">0") -> 3 | H4: =COUNTIF(V6唯一映射!$C$2:$C$101,$A4) -> 3 | I4: =G4/H4 -> 1 | J4: =IF(C4=0,0,E4/C4) -> 1
A5: C04 | B5: 动物物体载具主体生成 | C5: =SUMIF(统计辅助_勿改!$B$2:$B$2944,$A5,统计辅助_勿改!$C$2:$C$2944) -> 150 | D5: =C5/覆盖概览!$B$4 -> 0.33482143 | E5: =COUNTIF(检查点拆解!$D$2:$D$2944,$A5) -> 154 | F5: =E5/覆盖概览!$B$5 -> 0.052327557 | G5: =COUNTIFS(三级标签覆盖!$A$2:$A$101,$A5,三级标签覆盖!$F$2:$F$101,">0") -> 3 | H5: =COUNTIF(V6唯一映射!$C$2:$C$101,$A5) -> 3 | I5: =G5/H5 -> 1 | J5: =IF(C5=0,0,E5/C5) -> 1.0266667
A6: C05 | B6: 空间与环境场景生成 | C6: =SUMIF(统计辅助_勿改!$B$2:$B$2944,$A6,统计辅助_勿改!$C$2:$C$2944) -> 100 | D6: =C6/覆盖概览!$B$4 -> 0.22321429 | E6: =COUNTIF(检查点拆解!$D$2:$D$2944,$A6) -> 100 | F6: =E6/覆盖概览!$B$5 -> 0.033978933 | G6: =COUNTIFS(三级标签覆盖!$A$2:$A$101,$A6,三级标签覆盖!$F$2:$F$101,">0") -> 3 | H6: =COUNTIF(V6唯一映射!$C$2:$C$101,$A6) -> 3 | I6: =G6/H6 -> 1 | J6: =IF(C6=0,0,E6/C6) -> 1
A7: C06 | B7: 面部结构表情与口部操作 | C7: =SUMIF(统计辅助_勿改!$B$2:$B$2944,$A7,统计辅助_勿改!$C$2:$C$2944) -> 114 | D7: =C7/覆盖概览!$B$4 -> 0.25446429 | E7: =COUNTIF(检查点拆解!$D$2:$D$2944,$A7) -> 159 | F7: =E7/覆盖概览!$B$5 -> 0.054026504 | G7: =COUNTIFS(三级标签覆盖!$A$2:$A$101,$A7,三级标签覆盖!$F$2:$F$101,">0") -> 3 | H7: =COUNTIF(V6唯一映射!$C$2:$C$101,$A7) -> 3 | I7: =G7/H7 -> 1 | J7: =IF(C7=0,0,E7/C7) -> 1.3947368
A8: C07 | B8: 手部结构与精细动作 | C8: =SUMIF(统计辅助_勿改!$B$2:$B$2944,$A8,统计辅助_勿改!$C$2:$C$2944) -> 8 | D8: =C8/覆盖概览!$B$4 -> 0.017857143 | E8: =COUNTIF(检查点拆解!$D$2:$D$2944,$A8) -> 8 | F8: =E8/覆盖概览!$B$5 -> 0.0027183146 | G8: =COUNTIFS(三级标签覆盖!$A$2:$A$101,$A8,三级标签覆盖!$F$2:$F$101,">0") -> 3 | H8: =COUNTIF(V6唯一映射!$C$2:$C$101,$A8) -> 3 | I8: =G8/H8 -> 1 | J8: =IF(C8=0,0,E8/C8) -> 1
A9: C08 | B9: 整体人体结构与基础移动 | C9: =SUMIF(统计辅助_勿改!$B$2:$B$2944,$A9,统计辅助_勿改!$C$2:$C$2944) -> 88 | D9: =C9/覆盖概览!$B$4 -> 0.19642857 | E9: =COUNTIF(检查点拆解!$D$2:$D$2944,$A9) -> 96 | F9: =E9/覆盖概览!$B$5 -> 0.032619776 | G9: =COUNTIFS(三级标签覆盖!$A$2:$A$101,$A9,三级标签覆盖!$F$2:$F$101,">0") -> 4 | H9: =COUNTIF(V6唯一映射!$C$2:$C$101,$A9) -> 4 | I9: =G9/H9 -> 1 | J9: =IF(C9=0,0,E9/C9) -> 1.0909091
A10: C09 | B10: 功能动作与力量负重 | C10: =SUMIF(统计辅助_勿改!$B$2:$B$2944,$A10,统计辅助_勿改!$C$2:$C$2944) -> 24 | D10: =C10/覆盖概览!$B$4 -> 0.053571429 | E10: =COUNTIF(检查点拆解!$D$2:$D$2944,$A10) -> 24 | F10: =E10/覆盖概览!$B$5 -> 0.0081549439 | G10: =COUNTIFS(三级标签覆盖!$A$2:$A$101,$A10,三级标签覆盖!$F$2:$F$101,">0") -> 2 | H10: =COUNTIF(V6唯一映射!$C$2:$C$101,$A10) -> 2 | I10: =G10/H10 -> 1 | J10: =IF(C10=0,0,E10/C10) -> 1
A11: C10 | B11: 竞技体育运动 | C11: =SUMIF(统计辅助_勿改!$B$2:$B$2944,$A11,统计辅助_勿改!$C$2:$C$2944) -> 10 | D11: =C11/覆盖概览!$B$4 -> 0.022321429 | E11: =COUNTIF(检查点拆解!$D$2:$D$2944,$A11) -> 10 | F11: =E11/覆盖概览!$B$5 -> 0.0033978933 | G11: =COUNTIFS(三级标签覆盖!$A$2:$A$101,$A11,三级标签覆盖!$F$2:$F$101,">0") -> 1 | H11: =COUNTIF(V6唯一映射!$C$2:$C$101,$A11) -> 1 | I11: =G11/H11 -> 1 | J11: =IF(C11=0,0,E11/C11) -> 1
A12: C11 | B12: 舞蹈编排与节律运动 | C12: =SUMIF(统计辅助_勿改!$B$2:$B$2944,$A12,统计辅助_勿改!$C$2:$C$2944) -> 42 | D12: =C12/覆盖概览!$B$4 -> 0.09375 | E12: =COUNTIF(检查点拆解!$D$2:$D$2944,$A12) -> 42 | F12: =E12/覆盖概览!$B$5 -> 0.014271152 | G12: =COUNTIFS(三级标签覆盖!$A$2:$A$101,$A12,三级标签覆盖!$F$2:$F$101,">0") -> 1 | H12: =COUNTIF(V6唯一映射!$C$2:$C$101,$A12) -> 1 | I12: =G12/H12 -> 1 | J12: =IF(C12=0,0,E12/C12) -> 1
A13: C12 | B13: 体操跑酷、跌倒受击与恢复 | C13: =SUMIF(统计辅助_勿改!$B$2:$B$2944,$A13,统计辅助_勿改!$C$2:$C$2944) -> 29 | D13: =C13/覆盖概览!$B$4 -> 0.064732143 | E13: =COUNTIF(检查点拆解!$D$2:$D$2944,$A13) -> 30 | F13: =E13/覆盖概览!$B$5 -> 0.01019368 | G13: =COUNTIFS(三级标签覆盖!$A$2:$A$101,$A13,三级标签覆盖!$F$2:$F$101,">0") -> 2 | H13: =COUNTIF(V6唯一映射!$C$2:$C$101,$A13) -> 2 | I13: =G13/H13 -> 1 | J13: =IF(C13=0,0,E13/C13) -> 1.0344828
A14: C13 | B14: 衣物头发与附属随动 | C14: =SUMIF(统计辅助_勿改!$B$2:$B$2944,$A14,统计辅助_勿改!$C$2:$C$2944) -> 8 | D14: =C14/覆盖概览!$B$4 -> 0.017857143 | E14: =COUNTIF(检查点拆解!$D$2:$D$2944,$A14) -> 8 | F14: =E14/覆盖概览!$B$5 -> 0.0027183146 | G14: =COUNTIFS(三级标签覆盖!$A$2:$A$101,$A14,三级标签覆盖!$F$2:$F$101,">0") -> 1 | H14: =COUNTIF(V6唯一映射!$C$2:$C$101,$A14) -> 1 | I14: =G14/H14 -> 1 | J14: =IF(C14=0,0,E14/C14) -> 1
A15: C14 | B15: 多主体容量与精确数量 | C15: =SUMIF(统计辅助_勿改!$B$2:$B$2944,$A15,统计辅助_勿改!$C$2:$C$2944) -> 75 | D15: =C15/覆盖概览!$B$4 -> 0.16741071 | E15: =COUNTIF(检查点拆解!$D$2:$D$2944,$A15) -> 75 | F15: =E15/覆盖概览!$B$5 -> 0.0254842 | G15: =COUNTIFS(三级标签覆盖!$A$2:$A$101,$A15,三级标签覆盖!$F$2:$F$101,">0") -> 3 | H15: =COUNTIF(V6唯一映射!$C$2:$C$101,$A15) -> 4 | I15: =G15/H15 -> 0.75 | J15: =IF(C15=0,0,E15/C15) -> 1
A16: C15 | B16: 多主体独立、同步与团队组织 | C16: =SUMIF(统计辅助_勿改!$B$2:$B$2944,$A16,统计辅助_勿改!$C$2:$C$2944) -> 54 | D16: =C16/覆盖概览!$B$4 -> 0.12053571 | E16: =COUNTIF(检查点拆解!$D$2:$D$2944,$A16) -> 56 | F16: =E16/覆盖概览!$B$5 -> 0.019028203 | G16: =COUNTIFS(三级标签覆盖!$A$2:$A$101,$A16,三级标签覆盖!$F$2:$F$101,">0") -> 3 | H16: =COUNTIF(V6唯一映射!$C$2:$C$101,$A16) -> 3 | I16: =G16/H16 -> 1 | J16: =IF(C16=0,0,E16/C16) -> 1.037037
A17: C16 | B17: 多主体身份属性与归属稳定 | C17: =SUMIF(统计辅助_勿改!$B$2:$B$2944,$A17,统计辅助_勿改!$C$2:$C$2944) -> 13 | D17: =C17/覆盖概览!$B$4 -> 0.029017857 | E17: =COUNTIF(检查点拆解!$D$2:$D$2944,$A17) -> 13 | F17: =E17/覆盖概览!$B$5 -> 0.0044172613 | G17: =COUNTIFS(三级标签覆盖!$A$2:$A$101,$A17,三级标签覆盖!$F$2:$F$101,">0") -> 1 | H17: =COUNTIF(V6唯一映射!$C$2:$C$101,$A17) -> 4 | I17: =G17/H17 -> 0.25 | J17: =IF(C17=0,0,E17/C17) -> 1
A18: C17 | B18: 非人主体运动 | C18: =SUMIF(统计辅助_勿改!$B$2:$B$2944,$A18,统计辅助_勿改!$C$2:$C$2944) -> 92 | D18: =C18/覆盖概览!$B$4 -> 0.20535714 | E18: =COUNTIF(检查点拆解!$D$2:$D$2944,$A18) -> 98 | F18: =E18/覆盖概览!$B$5 -> 0.033299354 | G18: =COUNTIFS(三级标签覆盖!$A$2:$A$101,$A18,三级标签覆盖!$F$2:$F$101,">0") -> 6 | H18: =COUNTIF(V6唯一映射!$C$2:$C$101,$A18) -> 6 | I18: =G18/H18 -> 1 | J18: =IF(C18=0,0,E18/C18) -> 1.0652174
A19: C18 | B19: 人-物与专业器械操作 | C19: =SUMIF(统计辅助_勿改!$B$2:$B$2944,$A19,统计辅助_勿改!$C$2:$C$2944) -> 66 | D19: =C19/覆盖概览!$B$4 -> 0.14732143 | E19: =COUNTIF(检查点拆解!$D$2:$D$2944,$A19) -> 66 | F19: =E19/覆盖概览!$B$5 -> 0.022426096 | G19: =COUNTIFS(三级标签覆盖!$A$2:$A$101,$A19,三级标签覆盖!$F$2:$F$101,">0") -> 4 | H19: =COUNTIF(V6唯一映射!$C$2:$C$101,$A19) -> 4 | I19: =G19/H19 -> 1 | J19: =IF(C19=0,0,E19/C19) -> 1
A20: C19 | B20: 人际交流接触与协力 | C20: =SUMIF(统计辅助_勿改!$B$2:$B$2944,$A20,统计辅助_勿改!$C$2:$C$2944) -> 20 | D20: =C20/覆盖概览!$B$4 -> 0.044642857 | E20: =COUNTIF(检查点拆解!$D$2:$D$2944,$A20) -> 20 | F20: =E20/覆盖概览!$B$5 -> 0.0067957866 | G20: =COUNTIFS(三级标签覆盖!$A$2:$A$101,$A20,三级标签覆盖!$F$2:$F$101,">0") -> 3 | H20: =COUNTIF(V6唯一映射!$C$2:$C$101,$A20) -> 3 | I20: =G20/H20 -> 1 | J20: =IF(C20=0,0,E20/C20) -> 1
A21: C20 | B21: 武器与徒手打斗 | C21: =SUMIF(统计辅助_勿改!$B$2:$B$2944,$A21,统计辅助_勿改!$C$2:$C$2944) -> 21 | D21: =C21/覆盖概览!$B$4 -> 0.046875 | E21: =COUNTIF(检查点拆解!$D$2:$D$2944,$A21) -> 21 | F21: =E21/覆盖概览!$B$5 -> 0.0071355759 | G21: =COUNTIFS(三级标签覆盖!$A$2:$A$101,$A21,三级标签覆盖!$F$2:$F$101,">0") -> 1 | H21: =COUNTIF(V6唯一映射!$C$2:$C$101,$A21) -> 1 | I21: =G21/H21 -> 1 | J21: =IF(C21=0,0,E21/C21) -> 1
A22: C21 | B22: 骑乘操控与跨类型环境交互 | C22: =SUMIF(统计辅助_勿改!$B$2:$B$2944,$A22,统计辅助_勿改!$C$2:$C$2944) -> 15 | D22: =C22/覆盖概览!$B$4 -> 0.033482143 | E22: =COUNTIF(检查点拆解!$D$2:$D$2944,$A22) -> 15 | F22: =E22/覆盖概览!$B$5 -> 0.00509684 | G22: =COUNTIFS(三级标签覆盖!$A$2:$A$101,$A22,三级标签覆盖!$F$2:$F$101,">0") -> 1 | H22: =COUNTIF(V6唯一映射!$C$2:$C$101,$A22) -> 1 | I22: =G22/H22 -> 1 | J22: =IF(C22=0,0,E22/C22) -> 1
A23: C22 | B23: 空间朝向尺度与遮挡关系 | C23: =SUMIF(统计辅助_勿改!$B$2:$B$2944,$A23,统计辅助_勿改!$C$2:$C$2944) -> 0 | D23: =C23/覆盖概览!$B$4 -> 0 | E23: =COUNTIF(检查点拆解!$D$2:$D$2944,$A23) -> 0 | F23: =E23/覆盖概览!$B$5 -> 0 | G23: =COUNTIFS(三级标签覆盖!$A$2:$A$101,$A23,三级标签覆盖!$F$2:$F$101,">0") -> 0 | H23: =COUNTIF(V6唯一映射!$C$2:$C$101,$A23) -> 2 | I23: =G23/H23 -> 0 | J23: =IF(C23=0,0,E23/C23) -> 0
A24: C23 | B24: 刚体接触轨迹与碰撞物理 | C24: =SUMIF(统计辅助_勿改!$B$2:$B$2944,$A24,统计辅助_勿改!$C$2:$C$2944) -> 94 | D24: =C24/覆盖概览!$B$4 -> 0.20982143 | E24: =COUNTIF(检查点拆解!$D$2:$D$2944,$A24) -> 108 | F24: =E24/覆盖概览!$B$5 -> 0.036697248 | G24: =COUNTIFS(三级标签覆盖!$A$2:$A$101,$A24,三级标签覆盖!$F$2:$F$101,">0") -> 3 | H24: =COUNTIF(V6唯一映射!$C$2:$C$101,$A24) -> 3 | I24: =G24/H24 -> 1 | J24: =IF(C24=0,0,E24/C24) -> 1.1489362
A25: C24 | B25: 柔体流体状态变化与世界因果 | C25: =SUMIF(统计辅助_勿改!$B$2:$B$2944,$A25,统计辅助_勿改!$C$2:$C$2944) -> 196 | D25: =C25/覆盖概览!$B$4 -> 0.4375 | E25: =COUNTIF(检查点拆解!$D$2:$D$2944,$A25) -> 269 | F25: =E25/覆盖概览!$B$5 -> 0.09140333 | G25: =COUNTIFS(三级标签覆盖!$A$2:$A$101,$A25,三级标签覆盖!$F$2:$F$101,">0") -> 6 | H25: =COUNTIF(V6唯一映射!$C$2:$C$101,$A25) -> 6 | I25: =G25/H25 -> 1 | J25: =IF(C25=0,0,E25/C25) -> 1.372449
A26: C25 | B26: 速度节奏步骤与同步 | C26: =SUMIF(统计辅助_勿改!$B$2:$B$2944,$A26,统计辅助_勿改!$C$2:$C$2944) -> 207 | D26: =C26/覆盖概览!$B$4 -> 0.46205357 | E26: =COUNTIF(检查点拆解!$D$2:$D$2944,$A26) -> 233 | F26: =E26/覆盖概览!$B$5 -> 0.079170914 | G26: =COUNTIFS(三级标签覆盖!$A$2:$A$101,$A26,三级标签覆盖!$F$2:$F$101,">0") -> 4 | H26: =COUNTIF(V6唯一映射!$C$2:$C$101,$A26) -> 4 | I26: =G26/H26 -> 1 | J26: =IF(C26=0,0,E26/C26) -> 1.1256039
A27: C26 | B27: 主体场景与接触跨帧一致性 | C27: =SUMIF(统计辅助_勿改!$B$2:$B$2944,$A27,统计辅助_勿改!$C$2:$C$2944) -> 119 | D27: =C27/覆盖概览!$B$4 -> 0.265625 | E27: =COUNTIF(检查点拆解!$D$2:$D$2944,$A27) -> 128 | F27: =E27/覆盖概览!$B$5 -> 0.043493034 | G27: =COUNTIFS(三级标签覆盖!$A$2:$A$101,$A27,三级标签覆盖!$F$2:$F$101,">0") -> 2 | H27: =COUNTIF(V6唯一映射!$C$2:$C$101,$A27) -> 2 | I27: =G27/H27 -> 1 | J27: =IF(C27=0,0,E27/C27) -> 1.0756303
A28: C27 | B28: 镜头与摄影控制 | C28: =SUMIF(统计辅助_勿改!$B$2:$B$2944,$A28,统计辅助_勿改!$C$2:$C$2944) -> 223 | D28: =C28/覆盖概览!$B$4 -> 0.49776786 | E28: =COUNTIF(检查点拆解!$D$2:$D$2944,$A28) -> 345 | F28: =E28/覆盖概览!$B$5 -> 0.11722732 | G28: =COUNTIFS(三级标签覆盖!$A$2:$A$101,$A28,三级标签覆盖!$F$2:$F$101,">0") -> 7 | H28: =COUNTIF(V6唯一映射!$C$2:$C$101,$A28) -> 7 | I28: =G28/H28 -> 1 | J28: =IF(C28=0,0,E28/C28) -> 1.5470852
A29: C28 | B29: 构图光照材质与风格媒介 | C29: =SUMIF(统计辅助_勿改!$B$2:$B$2944,$A29,统计辅助_勿改!$C$2:$C$2944) -> 263 | D29: =C29/覆盖概览!$B$4 -> 0.58705357 | E29: =COUNTIF(检查点拆解!$D$2:$D$2944,$A29) -> 426 | F29: =E29/覆盖概览!$B$5 -> 0.14475025 | G29: =COUNTIFS(三级标签覆盖!$A$2:$A$101,$A29,三级标签覆盖!$F$2:$F$101,">0") -> 9 | H29: =COUNTIF(V6唯一映射!$C$2:$C$101,$A29) -> 9 | I29: =G29/H29 -> 1 | J29: =IF(C29=0,0,E29/C29) -> 1.6197719
A30: C29 | B30: 画面文字图形与界面 | C30: =SUMIF(统计辅助_勿改!$B$2:$B$2944,$A30,统计辅助_勿改!$C$2:$C$2944) -> 57 | D30: =C30/覆盖概览!$B$4 -> 0.12723214 | E30: =COUNTIF(检查点拆解!$D$2:$D$2944,$A30) -> 65 | F30: =E30/覆盖概览!$B$5 -> 0.022086306 | G30: =COUNTIFS(三级标签覆盖!$A$2:$A$101,$A30,三级标签覆盖!$F$2:$F$101,">0") -> 3 | H30: =COUNTIF(V6唯一映射!$C$2:$C$101,$A30) -> 3 | I30: =G30/H30 -> 1 | J30: =IF(C30=0,0,E30/C30) -> 1.1403509
A31: C30 | B31: 长镜头多镜头叙事与视觉特效 | C31: =SUMIF(统计辅助_勿改!$B$2:$B$2944,$A31,统计辅助_勿改!$C$2:$C$2944) -> 174 | D31: =C31/覆盖概览!$B$4 -> 0.38839286 | E31: =COUNTIF(检查点拆解!$D$2:$D$2944,$A31) -> 283 | F31: =E31/覆盖概览!$B$5 -> 0.096160381 | G31: =COUNTIFS(三级标签覆盖!$A$2:$A$101,$A31,三级标签覆盖!$F$2:$F$101,">0") -> 5 | H31: =COUNTIF(V6唯一映射!$C$2:$C$101,$A31) -> 5 | I31: =G31/H31 -> 1 | J31: =IF(C31=0,0,E31/C31) -> 1.6264368

Sheet 三级标签覆盖
A1: 核心能力ID | B1: 核心能力名称 | C1: 三级标签ID | D1: 三级标签名称 | E1: 题目覆盖数 | F1: 检查点数 | G1: 检查点占比 | H1: 覆盖状态
A2: C01 | B2: 指令语义与排除约束 | C2: D01.01.01 | D2: 常见直接指令理解 | E2: =SUMIF(统计辅助_勿改!$D$2:$D$2944,$C2,统计辅助_勿改!$E$2:$E$2944) -> 14 | F2: =COUNTIF(检查点拆解!$F$2:$F$2944,$C2) -> 14 | G2: =F2/覆盖概览!$B$5 -> 0.0047570506 | H2: =IF(F2=0,"未覆盖","已覆盖") -> 已覆盖
A3: C01 | B3: 指令语义与排除约束 | C3: D01.01.02 | D3: 长尾与专业概念理解 | E3: =SUMIF(统计辅助_勿改!$D$2:$D$2944,$C3,统计辅助_勿改!$E$2:$E$2944) -> 0 | F3: =COUNTIF(检查点拆解!$F$2:$F$2944,$C3) -> 0 | G3: =F3/覆盖概览!$B$5 -> 0 | H3: =IF(F3=0,"未覆盖","已覆盖") -> 未覆盖
A4: C01 | B4: 指令语义与排除约束 | C4: D01.01.03 | D4: 否定与排除约束 | E4: =SUMIF(统计辅助_勿改!$D$2:$D$2944,$C4,统计辅助_勿改!$E$2:$E$2944) -> 1 | F4: =COUNTIF(检查点拆解!$F$2:$F$2944,$C4) -> 1 | G4: =F4/覆盖概览!$B$5 -> 0.00033978933 | H4: =IF(F4=0,"未覆盖","已覆盖") -> 已覆盖
A5: C01 | B5: 指令语义与排除约束 | C5: D01.01.04 | D5: 指代与角色消歧 | E5: =SUMIF(统计辅助_勿改!$D$2:$D$2944,$C5,统计辅助_勿改!$E$2:$E$2944) -> 0 | F5: =COUNTIF(检查点拆解!$F$2:$F$2944,$C5) -> 0 | G5: =F5/覆盖概览!$B$5 -> 0 | H5: =IF(F5=0,"未覆盖","已覆盖") -> 未覆盖
A6: C02 | B6: 组合约束与时序理解 | C6: D01.02.01 | D6: 多条件组合遵循 | E6: =SUMIF(统计辅助_勿改!$D$2:$D$2944,$C6,统计辅助_勿改!$E$2:$E$2944) -> 0 | F6: =COUNTIF(检查点拆解!$F$2:$F$2944,$C6) -> 0 | G6: =F6/覆盖概览!$B$5 -> 0 | H6: =IF(F6=0,"未覆盖","已覆盖") -> 未覆盖
A7: C02 | B7: 组合约束与时序理解 | C7: D01.02.02 | D7: 结构化时序指令理解 | E7: =SUMIF(统计辅助_勿改!$D$2:$D$2944,$C7,统计辅助_勿改!$E$2:$E$2944) -> 1 | F7: =COUNTIF(检查点拆解!$F$2:$F$2944,$C7) -> 1 | G7: =F7/覆盖概览!$B$5 -> 0.00033978933 | H7: =IF(F7=0,"未覆盖","已覆盖") -> 已覆盖
A8: C02 | B8: 组合约束与时序理解 | C8: D01.02.03 | D8: 开放Prompt合理补全 | E8: =SUMIF(统计辅助_勿改!$D$2:$D$2944,$C8,统计辅助_勿改!$E$2:$E$2944) -> 2 | F8: =COUNTIF(检查点拆解!$F$2:$F$2944,$C8) -> 2 | G8: =F8/覆盖概览!$B$5 -> 0.00067957866 | H8: =IF(F8=0,"未覆盖","已覆盖") -> 已覆盖
A9: C03 | B9: 人物与角色主体生成 | C9: D02.01.01 | D9: 写实人物主体 | E9: =SUMIF(统计辅助_勿改!$D$2:$D$2944,$C9,统计辅助_勿改!$E$2:$E$2944) -> 63 | F9: =COUNTIF(检查点拆解!$F$2:$F$2944,$C9) -> 63 | G9: =F9/覆盖概览!$B$5 -> 0.021406728 | H9: =IF(F9=0,"未覆盖","已覆盖") -> 已覆盖
A10: C03 | B10: 人物与角色主体生成 | C10: D02.01.02 | D10: 风格化人物角色 | E10: =SUMIF(统计辅助_勿改!$D$2:$D$2944,$C10,统计辅助_勿改!$E$2:$E$2944) -> 1 | F10: =COUNTIF(检查点拆解!$F$2:$F$2944,$C10) -> 1 | G10: =F10/覆盖概览!$B$5 -> 0.00033978933 | H10: =IF(F10=0,"未覆盖","已覆盖") -> 已覆盖
A11: C03 | B11: 人物与角色主体生成 | C11: D02.01.03 | D11: 人物多样性与特殊形态 | E11: =SUMIF(统计辅助_勿改!$D$2:$D$2944,$C11,统计辅助_勿改!$E$2:$E$2944) -> 9 | F11: =COUNTIF(检查点拆解!$F$2:$F$2944,$C11) -> 9 | G11: =F11/覆盖概览!$B$5 -> 0.003058104 | H11: =IF(F11=0,"未覆盖","已覆盖") -> 已覆盖
A12: C04 | B12: 动物物体载具主体生成 | C12: D02.02.01 | D12: 动物与生物主体 | E12: =SUMIF(统计辅助_勿改!$D$2:$D$2944,$C12,统计辅助_勿改!$E$2:$E$2944) -> 66 | F12: =COUNTIF(检查点拆解!$F$2:$F$2944,$C12) -> 66 | G12: =F12/覆盖概览!$B$5 -> 0.022426096 | H12: =IF(F12=0,"未覆盖","已覆盖") -> 已覆盖
A13: C04 | B13: 动物物体载具主体生成 | C13: D02.02.02 | D13: 日常物体与食品主体 | E13: =SUMIF(统计辅助_勿改!$D$2:$D$2944,$C13,统计辅助_勿改!$E$2:$E$2944) -> 33 | F13: =COUNTIF(检查点拆解!$F$2:$F$2944,$C13) -> 33 | G13: =F13/覆盖概览!$B$5 -> 0.011213048 | H13: =IF(F13=0,"未覆盖","已覆盖") -> 已覆盖
... A101: C30 | B101: 长镜头多镜头叙事与视觉特效 | C101: D15.02.01 | D101: 动态特效与超现实变形 | E101: =SUMIF(统计辅助_勿改!$D$2:$D$2944,$C101,统计辅助_勿改!$E$2:$E$2944) -> 26 | F101: =COUNTIF(检查点拆解!$F$2:$F$2944,$C101) -> 26 | G101: =F101/覆盖概览!$B$5 -> 0.0088345226 | H101: =IF(F101=0,"未覆盖","已覆盖") -> 已覆盖

Sheet 统计辅助_勿改
A1: 题目ID | B1: 核心能力ID | C1: 能力-题目首次出现 | D1: 三级标签ID | E1: 标签-题目首次出现
A2: =检查点拆解!A2 -> Q0001 | B2: =检查点拆解!D2 -> C30 | C2: =--(COUNTIFS($A$2:A2,A2,$B$2:B2,B2)=1) -> 1 | D2: =检查点拆解!F2 -> D15.01.02 | E2: =--(COUNTIFS($A$2:A2,A2,$D$2:D2,D2)=1) -> 1
A3: =检查点拆解!A3 -> Q0001 | B3: =检查点拆解!D3 -> C18 | C3: =--(COUNTIFS($A$2:A3,A3,$B$2:B3,B3)=1) -> 1 | D3: =检查点拆解!F3 -> D07.01.02 | E3: =--(COUNTIFS($A$2:A3,A3,$D$2:D3,D3)=1) -> 1
A4: =检查点拆解!A4 -> Q0001 | B4: =检查点拆解!D4 -> C30 | C4: =--(COUNTIFS($A$2:A4,A4,$B$2:B4,B4)=1) -> 0 | D4: =检查点拆解!F4 -> D15.01.03 | E4: =--(COUNTIFS($A$2:A4,A4,$D$2:D4,D4)=1) -> 1
A5: =检查点拆解!A5 -> Q0001 | B5: =检查点拆解!D5 -> C27 | C5: =--(COUNTIFS($A$2:A5,A5,$B$2:B5,B5)=1) -> 1 | D5: =检查点拆解!F5 -> D11.01.02 | E5: =--(COUNTIFS($A$2:A5,A5,$D$2:D5,D5)=1) -> 1
A6: =检查点拆解!A6 -> Q0001 | B6: =检查点拆解!D6 -> C28 | C6: =--(COUNTIFS($A$2:A6,A6,$B$2:B6,B6)=1) -> 1 | D6: =检查点拆解!F6 -> D13.02.01 | E6: =--(COUNTIFS($A$2:A6,A6,$D$2:D6,D6)=1) -> 1
A7: =检查点拆解!A7 -> Q0001 | B7: =检查点拆解!D7 -> C28 | C7: =--(COUNTIFS($A$2:A7,A7,$B$2:B7,B7)=1) -> 0 | D7: =检查点拆解!F7 -> D12.01.01 | E7: =--(COUNTIFS($A$2:A7,A7,$D$2:D7,D7)=1) -> 1
A8: =检查点拆解!A8 -> Q0001 | B8: =检查点拆解!D8 -> C04 | C8: =--(COUNTIFS($A$2:A8,A8,$B$2:B8,B8)=1) -> 1 | D8: =检查点拆解!F8 -> D02.02.01 | E8: =--(COUNTIFS($A$2:A8,A8,$D$2:D8,D8)=1) -> 1
A9: =检查点拆解!A9 -> Q0002 | B9: =检查点拆解!D9 -> C20 | C9: =--(COUNTIFS($A$2:A9,A9,$B$2:B9,B9)=1) -> 1 | D9: =检查点拆解!F9 -> D07.02.04 | E9: =--(COUNTIFS($A$2:A9,A9,$D$2:D9,D9)=1) -> 1
A10: =检查点拆解!A10 -> Q0002 | B10: =检查点拆解!D10 -> C14 | C10: =--(COUNTIFS($A$2:A10,A10,$B$2:B10,B10)=1) -> 1 | D10: =检查点拆解!F10 -> D08.01.01 | E10: =--(COUNTIFS($A$2:A10,A10,$D$2:D10,D10)=1) -> 1
A11: =检查点拆解!A11 -> Q0002 | B11: =检查点拆解!D11 -> C23 | C11: =--(COUNTIFS($A$2:A11,A11,$B$2:B11,B11)=1) -> 1 | D11: =检查点拆解!F11 -> D09.01.02 | E11: =--(COUNTIFS($A$2:A11,A11,$D$2:D11,D11)=1) -> 1
A12: =检查点拆解!A12 -> Q0002 | B12: =检查点拆解!D12 -> C24 | C12: =--(COUNTIFS($A$2:A12,A12,$B$2:B12,B12)=1) -> 1 | D12: =检查点拆解!F12 -> D09.02.02 | E12: =--(COUNTIFS($A$2:A12,A12,$D$2:D12,D12)=1) -> 1
A13: =检查点拆解!A13 -> Q0002 | B13: =检查点拆解!D13 -> C30 | C13: =--(COUNTIFS($A$2:A13,A13,$B$2:B13,B13)=1) -> 1 | D13: =检查点拆解!F13 -> D15.02.01 | E13: =--(COUNTIFS($A$2:A13,A13,$D$2:D13,D13)=1) -> 1
... A2944: =检查点拆解!A2944 -> Q0448 | B2944: =检查点拆解!D2944 -> C08 | C2944: =--(COUNTIFS($A$2:A2944,A2944,$B$2:B2944,B2944)=1) -> 1 | D2944: =检查点拆解!F2944 -> D04.01.03 | E2944: =--(COUNTIFS($A$2:A2944,A2944,$D$2:D2944,D2944)=1) -> 1
